{
    "postId": "202410250017257",
    "title": "Cuộc thi Lan tỏa năng lượng tích cực 2024: Người mẹ cưu mang hàng trăm đứa con tật nguyền",
    "content": "Bà Trần Thị Cẩm Giang (87 tuổi, TP.HCM) còn được gọi với cái tên thân thương là \"má Mười\". Hơn 36 năm qua bà đã dành trọn tình cảm, tiền bạc để chăm sóc, nuôi dưỡng và xây dựng 'Mái ấm Thiện Duyên'.\nCuộc thi Lan tỏa năng lượng tích cực 2024\nMái ấm được bà Giang xây dựng năm 1988, từ 3 trẻ nhỏ bị nhiễm chất độc da cam ban đầu, hiện đã có hơn 130 trẻ. Có em ba mẹ mang đến, có em bà nhìn thấy ngoài đường đem về nuôi, đa phần là tật nguyền bởi di chứng của chất độc dioxin.\nGiờ đây, dù tuổi cao, sức khỏe đã yếu nhưng ngày ngày má Mười vẫn chăm lo chu đáo từng miếng cơm, giấc ngủ cho những đứa trẻ.",
    "author": "NGUYỄN LAN NHI",
    "date": "25/10/2024 14:00 GMT+7",
    "category": "Nhịp sống trẻ",
    "url": "https://tuoitre.vn/cuoc-thi-lan-toa-nang-luong-tich-cuc-2024-nguoi-me-cuu-mang-hang-tram-dua-con-tat-nguyen-202410250017257.htm",
    "audio_podcast": "https://tts.mediacdn.vn/2024/10/25/tuoitre-nu-1-202410250017257.m4a",
    "comments": null
}